[
    {
        "year": "2025",
        "months": [
            {"gid": null, "title": "Janeiro"},
            {"gid": "188713452", "title": "Detalhamento Fevereiro"},
            {"gid": null, "title": "Fevereiro"},
            {"gid": "1395769621", "title": "Detalhamento Março"},
            {"gid": null, "title": "Março"},
            {"gid": "1290733147", "title": "Detalhamento Abril"},
            {"gid": null, "title": "Abril"},
            {"gid": "1431587853", "title": "Detalhamento Maio"},
            {"gid": null, "title": "Maio"},
            {"gid": "1492049402", "title": "Detalhamento Junho"},
            {"gid": null, "title": "Junho"},
            {"gid": "1367319679", "title": "Detalhamento Julho"},
            {"gid": null, "title": "Julho"},
            {"gid": "909328962", "title": "Detalhamento Agosto"},
            {"gid": null, "title": "Agosto"},
            {"gid": "416141512", "title": "Setembro"},
            {"gid": "504481287", "title": "Detalhamento Setembro"},
            {"gid": "1400233715", "title": "Outubro"},
            {"gid": "383334541", "title": "Detalhamento Outubro"},
            {"gid": "1549128555", "title": "Novembro"},
            {"gid": "251968822", "title": "Detalhamento Novembro"},
            {"gid": "913366685", "title": "Dezembro"},
            {"gid": "1024837", "title": "Detalhamento Dezembro"},
            {"gid": "320520459", "title": "Relatório Anual"}
        ]
    },
    {
        "year": "2026",
        "months": [
            {"gid": null, "title": "Janeiro"},
            {"gid": null, "title": "Detalhamento Janeiro"},
            {"gid": null, "title": "Fevereiro"},
            {"gid": null, "title": "Detalhamento Fevereiro"},
            {"gid": null, "title": "Março"},
            {"gid": null, "title": "Detalhamento Março"},
            {"gid": null, "title": "Abril"},
            {"gid": null, "title": "Detalhamento Abril"},
            {"gid": null, "title": "Maio"},
            {"gid": null, "title": "Detalhamento Maio"},
            {"gid": null, "title": "Junho"},
            {"gid": null, "title": "Detalhamento Junho"},
            {"gid": null, "title": "Julho"},
            {"gid": null, "title": "Detalhamento Julho"},
            {"gid": null, "title": "Agosto"},
            {"gid": null, "title": "Detalhamento Agosto"},
            {"gid": null, "title": "Setembro"},
            {"gid": null, "title": "Detalhamento Setembro"},
            {"gid": null, "title": "Outubro"},
            {"gid": null, "title": "Detalhamento Outubro"},
            {"gid": null, "title": "Novembro"},
            {"gid": null, "title": "Detalhamento Novembro"},
            {"gid": null, "title": "Dezembro"},
            {"gid": null, "title": "Detalhamento Dezembro"},
            {"gid": null, "title": "Relatório Anual"}
        ]
    }
]
